odoo/addons/website_sale_b2x_alt_price/README.rst
odoo/addons/website_sale_b2x_alt_price/__init__.py
odoo/addons/website_sale_b2x_alt_price/__manifest__.py
odoo/addons/website_sale_b2x_alt_price/i18n/ca.po
odoo/addons/website_sale_b2x_alt_price/i18n/es.po
odoo/addons/website_sale_b2x_alt_price/i18n/fr.po
odoo/addons/website_sale_b2x_alt_price/i18n/it.po
odoo/addons/website_sale_b2x_alt_price/i18n/pt_BR.po
odoo/addons/website_sale_b2x_alt_price/i18n/website_sale_b2x_alt_price.pot
odoo/addons/website_sale_b2x_alt_price/models/__init__.py
odoo/addons/website_sale_b2x_alt_price/models/product_template.py
odoo/addons/website_sale_b2x_alt_price/readme/CONFIGURE.md
odoo/addons/website_sale_b2x_alt_price/readme/CONTRIBUTORS.md
odoo/addons/website_sale_b2x_alt_price/readme/DESCRIPTION.md
odoo/addons/website_sale_b2x_alt_price/readme/ROADMAP.md
odoo/addons/website_sale_b2x_alt_price/readme/USAGE.md
odoo/addons/website_sale_b2x_alt_price/static/description/b2b-features.png
odoo/addons/website_sale_b2x_alt_price/static/description/b2c-features.png
odoo/addons/website_sale_b2x_alt_price/static/description/details-features.gif
odoo/addons/website_sale_b2x_alt_price/static/description/icon.png
odoo/addons/website_sale_b2x_alt_price/static/description/index.html
odoo/addons/website_sale_b2x_alt_price/static/description/toggle-detail.gif
odoo/addons/website_sale_b2x_alt_price/static/description/toggle-list.gif
odoo/addons/website_sale_b2x_alt_price/static/src/js/product_configurator_mixin.esm.js
odoo/addons/website_sale_b2x_alt_price/static/tests/tours/b2b.esm.js
odoo/addons/website_sale_b2x_alt_price/static/tests/tours/b2c.esm.js
odoo/addons/website_sale_b2x_alt_price/templates/product.xml
odoo/addons/website_sale_b2x_alt_price/tests/__init__.py
odoo/addons/website_sale_b2x_alt_price/tests/test_ui.py
odoo_addon_website_sale_b2x_alt_price-18.0.1.0.0.4.dist-info/METADATA
odoo_addon_website_sale_b2x_alt_price-18.0.1.0.0.4.dist-info/WHEEL
odoo_addon_website_sale_b2x_alt_price-18.0.1.0.0.4.dist-info/top_level.txt
odoo_addon_website_sale_b2x_alt_price-18.0.1.0.0.4.dist-info/RECORD
